mycliapp/__init__.py
mycliapp/main.py
mycliapp123-0.1.dist-info/METADATA
mycliapp123-0.1.dist-info/WHEEL
mycliapp123-0.1.dist-info/entry_points.txt
mycliapp123-0.1.dist-info/top_level.txt
mycliapp123-0.1.dist-info/RECORD
